<keymap version="1" name="Mac OS X 10.5 custom" parent="Mac OS X 10.5+">
  <action id="ChooseDebugConfiguration" />
  <action id="ChooseRunConfiguration" />
  <action id="Debug" />
  <action id="EditSource">
    <mouse-shortcut keystroke="button1" />
  </action>
  <action id="JRebel Debug">
    <keyboard-shortcut first-keystroke="shift ctrl f10" />
  </action>
  <action id="JRebel Executor">
    <keyboard-shortcut first-keystroke="shift f10" />
  </action>
  <action id="synchronizeProject">
    <keyboard-shortcut first-keystroke="shift ctrl meta f10" />
  </action>
</keymap>